{
  "summary": {
    "arm_A": {
      "delivery_mean": 0.036431623931623934,
      "consistency_mean": 0.018161683277962345,
      "n": 12
    },
    "arm_B": {
      "delivery_mean": 0.5684087643678161,
      "consistency_mean": 0.7429894989411513,
      "n": 12
    },
    "predictions": {
      "1_armA_delivery_ge_85": false,
      "1_armA_delivery": 0.036431623931623934,
      "2_armA_ge_armB_delivery": false,
      "2_armA_ge_armB_consistency": false,
      "2_discovery_load_bearing": false,
      "3_conflicts_total": 0,
      "3_conflicts_all_armA": false,
      "list_mediated_discoveries_armA": 28,
      "doctor_fires_total": 0
    }
  },
  "rows": [
    {
      "run_id": "m01_r1",
      "arm": "A",
      "task": "m01",
      "converged": true,
      "outcome": "converged",
      "delivery": 0.0,
      "delivery_detection_ok": true,
      "legacy_term_count": 44,
      "consistency": 0.011627906976744186,
      "consistency_detection_ok": true,
      "list_calls": 1,
      "list_mediated_discoveries": 3,
      "conflicts": 0,
      "doctor_cycles": 0,
      "defers": 0,
      "defer_wake_fires": 0
    },
    {
      "run_id": "m01_r2",
      "arm": "A",
      "task": "m01",
      "converged": true,
      "outcome": "converged",
      "delivery": 0.0,
      "delivery_detection_ok": true,
      "legacy_term_count": 44,
      "consistency": 0.011627906976744186,
      "consistency_detection_ok": true,
      "list_calls": 1,
      "list_mediated_discoveries": 3,
      "conflicts": 0,
      "doctor_cycles": 0,
      "defers": 0,
      "defer_wake_fires": 0
    },
    {
      "run_id": "m01_r3",
      "arm": "A",
      "task": "m01",
      "converged": true,
      "outcome": "converged",
      "delivery": 0.0,
      "delivery_detection_ok": true,
      "legacy_term_count": 44,
      "consistency": 0.011627906976744186,
      "consistency_detection_ok": true,
      "list_calls": 1,
      "list_mediated_discoveries": 3,
      "conflicts": 0,
      "doctor_cycles": 0,
      "defers": 0,
      "defer_wake_fires": 0
    },
    {
      "run_id": "m01_r4",
      "arm": "A",
      "task": "m01",
      "converged": true,
      "outcome": "converged",
      "delivery": 0.0,
      "delivery_detection_ok": true,
      "legacy_term_count": 44,
      "consistency": 0.011627906976744186,
      "consistency_detection_ok": true,
      "list_calls": 1,
      "list_mediated_discoveries": 3,
      "conflicts": 0,
      "doctor_cycles": 0,
      "defers": 0,
      "defer_wake_fires": 0
    },
    {
      "run_id": "m02_r1",
      "arm": "A",
      "task": "m02",
      "converged": true,
      "outcome": "converged",
      "delivery": 0.03333333333333333,
      "delivery_detection_ok": true,
      "legacy_term_count": 30,
      "consistency": 0.0,
      "consistency_detection_ok": true,
      "list_calls": 1,
      "list_mediated_discoveries": 2,
      "conflicts": 0,
      "doctor_cycles": 0,
      "defers": 0,
      "defer_wake_fires": 0
    },
    {
      "run_id": "m02_r2",
      "arm": "A",
      "task": "m02",
      "converged": true,
      "outcome": "converged",
      "delivery": 0.0,
      "delivery_detection_ok": true,
      "legacy_term_count": 24,
      "consistency": 0.0,
      "consistency_detection_ok": true,
      "list_calls": 1,
      "list_mediated_discoveries": 2,
      "conflicts": 0,
      "doctor_cycles": 0,
      "defers": 0,
      "defer_wake_fires": 0
    },
    {
      "run_id": "m02_r3",
      "arm": "A",
      "task": "m02",
      "converged": true,
      "outcome": "converged",
      "delivery": 0.0,
      "delivery_detection_ok": true,
      "legacy_term_count": 24,
      "consistency": 0.0,
      "consistency_detection_ok": true,
      "list_calls": 1,
      "list_mediated_discoveries": 2,
      "conflicts": 0,
      "doctor_cycles": 0,
      "defers": 15,
      "defer_wake_fires": 0
    },
    {
      "run_id": "m02_r4",
      "arm": "A",
      "task": "m02",
      "converged": true,
      "outcome": "converged",
      "delivery": 0.0,
      "delivery_detection_ok": true,
      "legacy_term_count": 24,
      "consistency": 0.0,
      "consistency_detection_ok": true,
      "list_calls": 1,
      "list_mediated_discoveries": 2,
      "conflicts": 0,
      "doctor_cycles": 0,
      "defers": 15,
      "defer_wake_fires": 0
    },
    {
      "run_id": "m03_r1",
      "arm": "A",
      "task": "m03",
      "converged": true,
      "outcome": "converged",
      "delivery": 0.11538461538461539,
      "delivery_detection_ok": true,
      "legacy_term_count": 104,
      "consistency": 0.05714285714285714,
      "consistency_detection_ok": true,
      "list_calls": 1,
      "list_mediated_discoveries": 2,
      "conflicts": 0,
      "doctor_cycles": 0,
      "defers": 0,
      "defer_wake_fires": 0
    },
    {
      "run_id": "m03_r2",
      "arm": "A",
      "task": "m03",
      "converged": true,
      "outcome": "converged",
      "delivery": 0.11538461538461539,
      "delivery_detection_ok": true,
      "legacy_term_count": 104,
      "consistency": 0.05714285714285714,
      "consistency_detection_ok": true,
      "list_calls": 1,
      "list_mediated_discoveries": 2,
      "conflicts": 0,
      "doctor_cycles": 0,
      "defers": 0,
      "defer_wake_fires": 0
    },
    {
      "run_id": "m03_r3",
      "arm": "A",
      "task": "m03",
      "converged": true,
      "outcome": "converged",
      "delivery": 0.11538461538461539,
      "delivery_detection_ok": true,
      "legacy_term_count": 104,
      "consistency": 0.05714285714285714,
      "consistency_detection_ok": true,
      "list_calls": 1,
      "list_mediated_discoveries": 2,
      "conflicts": 0,
      "doctor_cycles": 0,
      "defers": 0,
      "defer_wake_fires": 0
    },
    {
      "run_id": "m03_r4",
      "arm": "A",
      "task": "m03",
      "converged": true,
      "outcome": "converged",
      "delivery": 0.057692307692307696,
      "delivery_detection_ok": true,
      "legacy_term_count": 104,
      "consistency": 0.0,
      "consistency_detection_ok": true,
      "list_calls": 1,
      "list_mediated_discoveries": 2,
      "conflicts": 0,
      "doctor_cycles": 0,
      "defers": 0,
      "defer_wake_fires": 0
    },
    {
      "run_id": "m01_r1",
      "arm": "B",
      "task": "m01",
      "converged": true,
      "outcome": "converged",
      "delivery": 0.46875,
      "delivery_detection_ok": true,
      "legacy_term_count": 32,
      "consistency": 0.9302325581395349,
      "consistency_detection_ok": true,
      "list_calls": 0,
      "list_mediated_discoveries": 0,
      "conflicts": 0,
      "doctor_cycles": 0,
      "defers": 0,
      "defer_wake_fires": 0
    },
    {
      "run_id": "m01_r2",
      "arm": "B",
      "task": "m01",
      "converged": true,
      "outcome": "converged",
      "delivery": 0.46875,
      "delivery_detection_ok": true,
      "legacy_term_count": 32,
      "consistency": 0.9302325581395349,
      "consistency_detection_ok": true,
      "list_calls": 0,
      "list_mediated_discoveries": 0,
      "conflicts": 0,
      "doctor_cycles": 0,
      "defers": 0,
      "defer_wake_fires": 0
    },
    {
      "run_id": "m01_r3",
      "arm": "B",
      "task": "m01",
      "converged": true,
      "outcome": "converged",
      "delivery": 0.46875,
      "delivery_detection_ok": true,
      "legacy_term_count": 32,
      "consistency": 0.9302325581395349,
      "consistency_detection_ok": true,
      "list_calls": 0,
      "list_mediated_discoveries": 0,
      "conflicts": 0,
      "doctor_cycles": 0,
      "defers": 0,
      "defer_wake_fires": 0
    },
    {
      "run_id": "m01_r4",
      "arm": "B",
      "task": "m01",
      "converged": true,
      "outcome": "converged",
      "delivery": 0.02857142857142857,
      "delivery_detection_ok": true,
      "legacy_term_count": 35,
      "consistency": 0.11627906976744186,
      "consistency_detection_ok": true,
      "list_calls": 0,
      "list_mediated_discoveries": 0,
      "conflicts": 0,
      "doctor_cycles": 0,
      "defers": 0,
      "defer_wake_fires": 0
    },
    {
      "run_id": "m02_r1",
      "arm": "B",
      "task": "m02",
      "converged": true,
      "outcome": "converged",
      "delivery": 1.0,
      "delivery_detection_ok": true,
      "legacy_term_count": 16,
      "consistency": 1.0,
      "consistency_detection_ok": true,
      "list_calls": 0,
      "list_mediated_discoveries": 0,
      "conflicts": 0,
      "doctor_cycles": 0,
      "defers": 0,
      "defer_wake_fires": 0
    },
    {
      "run_id": "m02_r2",
      "arm": "B",
      "task": "m02",
      "converged": true,
      "outcome": "converged",
      "delivery": 1.0,
      "delivery_detection_ok": true,
      "legacy_term_count": 16,
      "consistency": 1.0,
      "consistency_detection_ok": true,
      "list_calls": 0,
      "list_mediated_discoveries": 0,
      "conflicts": 0,
      "doctor_cycles": 0,
      "defers": 0,
      "defer_wake_fires": 0
    },
    {
      "run_id": "m02_r3",
      "arm": "B",
      "task": "m02",
      "converged": true,
      "outcome": "converged",
      "delivery": 0.9375,
      "delivery_detection_ok": true,
      "legacy_term_count": 16,
      "consistency": 0.8571428571428571,
      "consistency_detection_ok": true,
      "list_calls": 0,
      "list_mediated_discoveries": 0,
      "conflicts": 0,
      "doctor_cycles": 0,
      "defers": 0,
      "defer_wake_fires": 0
    },
    {
      "run_id": "m02_r4",
      "arm": "B",
      "task": "m02",
      "converged": true,
      "outcome": "converged",
      "delivery": 0.5714285714285714,
      "delivery_detection_ok": true,
      "legacy_term_count": 7,
      "consistency": 0.75,
      "consistency_detection_ok": true,
      "list_calls": 0,
      "list_mediated_discoveries": 0,
      "conflicts": 0,
      "doctor_cycles": 0,
      "defers": 0,
      "defer_wake_fires": 0
    },
    {
      "run_id": "m03_r1",
      "arm": "B",
      "task": "m03",
      "converged": true,
      "outcome": "converged",
      "delivery": 0.46875,
      "delivery_detection_ok": true,
      "legacy_term_count": 32,
      "consistency": 0.6140350877192983,
      "consistency_detection_ok": true,
      "list_calls": 0,
      "list_mediated_discoveries": 0,
      "conflicts": 0,
      "doctor_cycles": 0,
      "defers": 19,
      "defer_wake_fires": 0
    },
    {
      "run_id": "m03_r2",
      "arm": "B",
      "task": "m03",
      "converged": true,
      "outcome": "converged",
      "delivery": 0.40625,
      "delivery_detection_ok": true,
      "legacy_term_count": 32,
      "consistency": 0.5614035087719298,
      "consistency_detection_ok": true,
      "list_calls": 0,
      "list_mediated_discoveries": 0,
      "conflicts": 0,
      "doctor_cycles": 0,
      "defers": 19,
      "defer_wake_fires": 0
    },
    {
      "run_id": "m03_r3",
      "arm": "B",
      "task": "m03",
      "converged": true,
      "outcome": "converged",
      "delivery": 0.6896551724137931,
      "delivery_detection_ok": true,
      "legacy_term_count": 29,
      "consistency": 0.7,
      "consistency_detection_ok": true,
      "list_calls": 0,
      "list_mediated_discoveries": 0,
      "conflicts": 0,
      "doctor_cycles": 0,
      "defers": 19,
      "defer_wake_fires": 0
    },
    {
      "run_id": "m03_r4",
      "arm": "B",
      "task": "m03",
      "converged": true,
      "outcome": "converged",
      "delivery": 0.3125,
      "delivery_detection_ok": true,
      "legacy_term_count": 32,
      "consistency": 0.5263157894736842,
      "consistency_detection_ok": true,
      "list_calls": 0,
      "list_mediated_discoveries": 0,
      "conflicts": 0,
      "doctor_cycles": 0,
      "defers": 19,
      "defer_wake_fires": 0
    }
  ]
}
